{
  "$id": "/api/pipes/xxxxxx-dimensions-collect/entity-types/sink",
  "$schema": "http://json-schema.org/schema#",
  "additionalProperties": true,
  "properties": {
    "Dimension10ID": {
      "type": "integer"
    },
    "Dimension5ID": {
      "type": "integer"
    },
    "Dimension6ID": {
      "type": "integer"
    },
    "Dimension7ID": {
      "type": "integer"
    },
    "Dimension8ID": {
      "type": "integer"
    },
    "Dimension9ID": {
      "type": "integer"
    },
    "ProjectTaskID": {
      "type": "integer"
    },
    "RegionID": {
      "type": "integer"
    },
    "ResponsibleID": {
      "type": "integer"
    },
    "StatusCode": {
      "type": "integer"
    },
    "UpdatedAt": {
      "type": "string",
      "description": "Datetime in ISO format"
    },
    "UpdatedBy": {
      "type": "string"
    }
  },
  "title": "Pipe sink entity type: xxxxxx-dimensions-collect",
  "type": "object"
}